[{"name":"create","palette":"118","spec":"create tap layout %s.inputOnly ","typeName":"","type":" ","code":"com.google.android.material.tabs.TabLayout %1$s \u003d new com.google.android.material.tabs.TabLayout(this);","color":"#FF6A1B9A"},{"name":"make","palette":"118","spec":"make %s.inputOnly tap layout scrollable","type":" ","typeName":"","color":"#FF6A1B9A","code":"%1$s.setTabMode(com.google.android.material.tabs.TabLayout.MODE_SCROLLABLE);"},{"name":"add","palette":"118","spec":"add %s.inputOnly to %s.inputOnly tap layout","typeName":"","type":" ","code":"%2$s.addTab(%2$s.newTab().setText(\"%1$s\"));","color":"#FF6A1B9A"},{"name":"set","palette":"118","spec":"set %m.view as %s.inputOnly tap layout","type":" ","typeName":"","color":"#FF6A1B9A","code":"%1$s.addView(%2$s);"},{"name":"select item","palette":"118","spec":"on %s.inputOnly  tap layout item selected","typeName":"","type":"c","code":"%s.addOnTabSelectedListener(new com.google.android.material.tabs.TabLayout.OnTabSelectedListener(){\n@Override\npublic void onTabSelected(com.google.android.material.tabs.TabLayout.Tab tab){\nswitch(tab.getText().toString()){\n%s\n}\n}\n@Override\npublic void onTabReselected(com.google.android.material.tabs.TabLayout.Tab tab){\n}\n@Override\npublic void onTabUnselected(com.google.android.material.tabs.TabLayout.Tab tab){\n}\n\n});","color":"#FF6A1B9A"},{"name":"case","palette":"118","spec":"case %s.inputOnly ","type":"c","typeName":"","color":"#FF6A1B9A","code":"case \"%s\":\n%s\nbreak;"}]